odoo/addons/repair_service/README.rst
odoo/addons/repair_service/__init__.py
odoo/addons/repair_service/__manifest__.py
odoo/addons/repair_service/i18n/es.po
odoo/addons/repair_service/i18n/it.po
odoo/addons/repair_service/i18n/repair_service.pot
odoo/addons/repair_service/models/__init__.py
odoo/addons/repair_service/models/repair_order.py
odoo/addons/repair_service/models/repair_service.py
odoo/addons/repair_service/readme/CONTEXT.md
odoo/addons/repair_service/readme/CONTRIBUTORS.md
odoo/addons/repair_service/readme/DESCRIPTION.md
odoo/addons/repair_service/readme/USAGE.md
odoo/addons/repair_service/security/ir.model.access.csv
odoo/addons/repair_service/security/ir_rule.xml
odoo/addons/repair_service/static/description/icon.png
odoo/addons/repair_service/static/description/index.html
odoo/addons/repair_service/tests/__init__.py
odoo/addons/repair_service/tests/test_repair_service.py
odoo/addons/repair_service/views/repair_views.xml
odoo_addon_repair_service-18.0.1.2.0.dist-info/METADATA
odoo_addon_repair_service-18.0.1.2.0.dist-info/WHEEL
odoo_addon_repair_service-18.0.1.2.0.dist-info/top_level.txt
odoo_addon_repair_service-18.0.1.2.0.dist-info/RECORD
